Metadata-Version: 1.0
Name: savemd
Version: 0.0.4
Summary: Conver a html to markdown.
Home-page: https://github.com/laixintao/savemd
Author: laixintao
Author-email: laixintao1995@163.com
License: MIT
Keywords: markdown html convert
Platform: UNKNOWN
